bison/__init__.py
bison/bison_.cp311-win_amd64.pyd
bison/convert.py
bison/node.py
bison/xmlifier.py
bison/c/bison_callback.c
bison/c/bison_callback.h
bison/c/bisondynlib-linux.c
bison/c/bisondynlib-win32.c
bison/c/bisondynlib.h
bison/cython/bison_.c
bison/cython/bison_.pyx
bison/winflexbison/FlexLexer.h
bison/winflexbison/README.txt
bison/winflexbison/UNISTD_ERROR.readme
bison/winflexbison/data/README
bison/winflexbison/data/bison.m4
bison/winflexbison/data/c++-skel.m4
bison/winflexbison/data/c++.m4
bison/winflexbison/data/c-like.m4
bison/winflexbison/data/c-skel.m4
bison/winflexbison/data/c.m4
bison/winflexbison/data/glr.c
bison/winflexbison/data/glr.cc
bison/winflexbison/data/java-skel.m4
bison/winflexbison/data/java.m4
bison/winflexbison/data/lalr1.cc
bison/winflexbison/data/lalr1.java
bison/winflexbison/data/local.mk
bison/winflexbison/data/location.cc
bison/winflexbison/data/stack.hh
bison/winflexbison/data/variant.hh
bison/winflexbison/data/yacc.c
bison/winflexbison/data/m4sugar/foreach.m4
bison/winflexbison/data/m4sugar/m4sugar.m4
bison/winflexbison/data/xslt/bison.xsl
bison/winflexbison/data/xslt/xml2dot.xsl
bison/winflexbison/data/xslt/xml2text.xsl
bison/winflexbison/data/xslt/xml2xhtml.xsl
pybison-0.6.4.data/scripts/bison2py
pybison-0.6.4.dist-info/LICENSE
pybison-0.6.4.dist-info/METADATA
pybison-0.6.4.dist-info/WHEEL
pybison-0.6.4.dist-info/top_level.txt
pybison-0.6.4.dist-info/RECORD
